COTRA/__init__.py
COTRA/animation.py
COTRA/export.py
COTRA/plot.py
COTRA/solver.py
cotra-1.0.2.dist-info/licenses/LICENSE
cotra-1.0.2.dist-info/METADATA
cotra-1.0.2.dist-info/WHEEL
cotra-1.0.2.dist-info/top_level.txt
cotra-1.0.2.dist-info/RECORD
