Metadata-Version: 2.4
Name: COTRA
Version: 1.0.2
Summary: A simple 1D contaminant transport simulation library
Author-email: Simone Pagliuca <pagliuca.simone01@gmail.com>
License: MIT
Project-URL: Homepage, https://github.com/simo-pagliu/COTRA
License-File: LICENSE
Requires-Dist: numpy
Requires-Dist: scipy
Requires-Dist: matplotlib
Dynamic: license-file
